smpl_doc/__init__.py
smpl_doc-1.2.0.dist-info/METADATA
smpl_doc-1.2.0.dist-info/WHEEL
smpl_doc-1.2.0.dist-info/licenses/LICENSE
smpl_doc-1.2.0.dist-info/RECORD
