Metadata-Version: 2.4
Name: smpl_doc
Version: 1.2.0
Summary: SiMPLe magic documentation
Project-URL: Documentation, https://smpl.readthedocs.io/en/latest/_autosummary/smpl_doc.doc.html#module-smpl_doc.dochttps://github.com/APN-Pucky/smpl_doc/
Project-URL: Issues, https://github.com/APN-Pucky/smpl_doc/issues
Project-URL: Source, https://github.com/APN-Pucky/smpl_doc/
Author-email: Alexander Puck Neuwirth <alexander@neuwirth-informatik.de>
License-File: LICENSE
Classifier: Development Status :: 4 - Beta
Classifier: Intended Audience :: Developers
Classifier: Intended Audience :: Science/Research
Classifier: License :: OSI Approved :: GNU General Public License v3 (GPLv3)
Classifier: Programming Language :: Python
Classifier: Programming Language :: Python :: 3.9
Classifier: Programming Language :: Python :: 3.10
Classifier: Programming Language :: Python :: 3.11
Classifier: Programming Language :: Python :: 3.12
Classifier: Programming Language :: Python :: 3.13
Classifier: Programming Language :: Python :: Implementation :: CPython
Classifier: Programming Language :: Python :: Implementation :: PyPy
Requires-Python: >=3.8
Requires-Dist: smpl>=1.5.0
Provides-Extra: dev
Requires-Dist: pre-commit; extra == 'dev'
Provides-Extra: docs
Requires-Dist: myst-parser; extra == 'docs'
Requires-Dist: numpydoc; extra == 'docs'
Requires-Dist: pandoc; extra == 'docs'
Requires-Dist: sphinx; extra == 'docs'
Requires-Dist: sphinx-autoapi; extra == 'docs'
Requires-Dist: sphinx-autobuild; extra == 'docs'
Requires-Dist: sphinx-rtd-theme; extra == 'docs'
Requires-Dist: sphinxcontrib-napoleon; extra == 'docs'
Requires-Dist: toml; extra == 'docs'
Provides-Extra: lint
Requires-Dist: ruff; extra == 'lint'
Provides-Extra: test
Requires-Dist: pytest; extra == 'test'
Requires-Dist: pytest-cov; extra == 'test'
Requires-Dist: pytest-profiling; extra == 'test'
